lib_py_comp/__init__.py
lib_py_comp/alg/__init__.py
lib_py_comp/alg/deserialization.py
lib_py_comp/alg/partitioning.py
lib_py_comp/alg/serialization.py
lib_py_comp/alg/typon_math.py
lib_py_comp/dsa/__init__.py
lib_py_comp/dsa/buffered_io.py
lib_py_comp/dsa/byte_array.py
lib_py_comp/dsa/delimited_io.py
lib_py_comp/dsa/file_io.py
lib_py_comp/dsa/kv_db.py
lib_py_comp/tests/__init__.py
lib_py_comp/tests/test_ba.py
lib_py_comp/tests/test_buffered.py
lib_py_comp/tests/test_delimited.py
lib_py_comp/tests/test_kv.py
lib_py_comp-0.0.3.dist-info/METADATA
lib_py_comp-0.0.3.dist-info/WHEEL
lib_py_comp-0.0.3.dist-info/top_level.txt
lib_py_comp-0.0.3.dist-info/RECORD
