Metadata-Version: 2.1
Name: lib-py-comp
Version: 0.0.3
Home-page: http://pypi.python.org/pypi/lib_py_comp/0.0.3
Author: hypothesisbase
Author-email: support@hypothesisbase.com
License: MIT
Requires-Dist: requests
Requires-Dist: leveldb
Requires-Dist: lib-py-parse
